bdown/__init__.py
bdown/block.py
bdown/block_fiddler.py
bdown/check.py
bdown/download.py
bdown/download_cmd.py
bdown/filesplitter.py
blockdownload-0.1.0.dist-info/METADATA
blockdownload-0.1.0.dist-info/WHEEL
blockdownload-0.1.0.dist-info/entry_points.txt
blockdownload-0.1.0.dist-info/licenses/LICENSE
blockdownload-0.1.0.dist-info/RECORD
