Metadata-Version: 2.4
Name: blockdownload
Version: 0.1.0
Dynamic: Summary
Project-URL: Home, https://github.com/WolfgangFahl/blockdownload
Project-URL: Documentation, http://wiki.bitplan.com/index.php/blockdownload
Project-URL: Source, https://github.com/WolfgangFahl/blockdownload
Author-email: Wolfgang Fahl <wf@bitplan.com>
Maintainer-email: Wolfgang Fahl <wf@bitplan.com>
License-Expression: Apache-2.0
License-File: LICENSE
Classifier: Programming Language :: Python
Classifier: Programming Language :: Python :: 3.10
Classifier: Programming Language :: Python :: 3.11
Classifier: Programming Language :: Python :: 3.12
Classifier: Programming Language :: Python :: 3.13
Requires-Python: >=3.10
Requires-Dist: pybasemkit>=0.0.3
Requires-Dist: requests>=2.32.4
Requires-Dist: tqdm>=4.66.5
Provides-Extra: test
